CHANGES.txt
LICENSE.txt
MANIFEST.in
README.md
README.txt
setup.py
django_proxy_users/__init__.py
django_proxy_users/context_processors.py
django_proxy_users/forms.py
django_proxy_users/models.py
django_proxy_users/settings.py
django_proxy_users/tests.py
django_proxy_users/urls.py
django_proxy_users/views.py
django_proxy_users.egg-info/PKG-INFO
django_proxy_users.egg-info/SOURCES.txt
django_proxy_users.egg-info/dependency_links.txt
django_proxy_users.egg-info/requires.txt
django_proxy_users.egg-info/top_level.txt
django_proxy_users/auth/__init__.py
django_proxy_users/auth/backends.py
django_proxy_users/static/jquery/jquery-1.8.2.js
django_proxy_users/static/jquery/jquery-1.8.2.min.js
django_proxy_users/static/twitter-bootstrap/css/bootstrap-responsive.css
django_proxy_users/static/twitter-bootstrap/css/bootstrap-responsive.min.css
django_proxy_users/static/twitter-bootstrap/css/bootstrap.css
django_proxy_users/static/twitter-bootstrap/css/bootstrap.min.css
django_proxy_users/static/twitter-bootstrap/img/glyphicons-halflings-white.png
django_proxy_users/static/twitter-bootstrap/img/glyphicons-halflings.png
django_proxy_users/static/twitter-bootstrap/js/bootstrap.js
django_proxy_users/static/twitter-bootstrap/js/bootstrap.min.js
django_proxy_users/templates/block/pagination.html
django_proxy_users/templates/django_proxy_users/home.html
django_proxy_users/templates/django_proxy_users/login.html
django_proxy_users/templates/django_proxy_users/login_as.html
django_proxy_users/templates/layouts/default.html