Metadata-Version: 1.0
Name: django-proxy-users
Version: 0.0.8
Summary: Authentication extension to enable proxy users in django.
Home-page: https://github.com/jturo/django-proxy-users.git
Author: Jesus Rodriguez
Author-email: jesus.rodriguez.ravelo@gmail.com
License: LICENSE.txt
Platform: UNKNOWN
Classifier: Environment :: Web Environment
Classifier: Framework :: Django
Classifier: Intended Audience :: Developers
Classifier: License :: OSI Approved :: BSD License
Classifier: Natural Language :: English
